{
    "prices": [
        {
            "timestamp": "2026-05-04 03:06:46",
            "underlying_prices": {
                "Bid": 62.4,
                "Ask": 63.64,
                "get_instrument_value": 62.61000061
            },
            "option_prices": [
                {
                    "contract_localSymbol": "FISV  260508C00050000",
                    "contract_strike": 50.0,
                    "contract_right": "C",
                    "Bid": -1.0,
                    "Ask": -1.0,
                    "IV": null,
                    "call_open_interest": 0.0,
                    "put_open_interest": 0.0,
                    "theta": null,
                    "delta": null,
                    "gamma": null,
                    "vega": null,
                    "price": 12.3991003
                },
                {
                    "contract_localSymbol": "FISV  260508C00051000",
                    "contract_strike": 51.0,
                    "contract_right": "C",
                    "Bid": -1.0,
                    "Ask": -1.0,
                    "IV": null,
                    "call_open_interest": 1.0,
                    "put_open_interest": 0.0,
                    "theta": null,
                    "delta": null,
                    "gamma": null,
                    "vega": null,
                    "price": 11.45510006
                },
                {
                    "contract_localSymbol": "FISV  260508C00052000",
                    "contract_strike": 52.0,
                    "contract_right": "C",
                    "Bid": -1.0,
                    "Ask": -1.0,
                    "IV": null,
                    "call_open_interest": 0.0,
                    "put_open_interest": 0.0,
                    "theta": null,
                    "delta": null,
                    "gamma": null,
                    "vega": null,
                    "price": 10.58030033
                },
                {
                    "contract_localSymbol": "FISV  260508C00053000",
                    "contract_strike": 53.0,
                    "contract_right": "C",
                    "Bid": -1.0,
                    "Ask": -1.0,
                    "IV": null,
                    "call_open_interest": 0.0,
                    "put_open_interest": 0.0,
                    "theta": null,
                    "delta": null,
                    "gamma": null,
                    "vega": null,
                    "price": 9.66806984
                },
                {
                    "contract_localSymbol": "FISV  260508C00054000",
                    "contract_strike": 54.0,
                    "contract_right": "C",
                    "Bid": -1.0,
                    "Ask": -1.0,
                    "IV": null,
                    "call_open_interest": 25.0,
                    "put_open_interest": 0.0,
                    "theta": null,
                    "delta": null,
                    "gamma": null,
                    "vega": null,
                    "price": 8.79500961
                },
                {
                    "contract_localSymbol": "FISV  260508C00055000",
                    "contract_strike": 55.0,
                    "contract_right": "C",
                    "Bid": -1.0,
                    "Ask": -1.0,
                    "IV": null,
                    "call_open_interest": 5.0,
                    "put_open_interest": 0.0,
                    "theta": null,
                    "delta": null,
                    "gamma": null,
                    "vega": null,
                    "price": 7.94854021
                },
                {
                    "contract_localSymbol": "FISV  260508C00056000",
                    "contract_strike": 56.0,
                    "contract_right": "C",
                    "Bid": -1.0,
                    "Ask": -1.0,
                    "IV": null,
                    "call_open_interest": 3.0,
                    "put_open_interest": 0.0,
                    "theta": null,
                    "delta": null,
                    "gamma": null,
                    "vega": null,
                    "price": 7.13761997
                },
                {
                    "contract_localSymbol": "FISV  260508C00057000",
                    "contract_strike": 57.0,
                    "contract_right": "C",
                    "Bid": -1.0,
                    "Ask": -1.0,
                    "IV": null,
                    "call_open_interest": 5.0,
                    "put_open_interest": 0.0,
                    "theta": null,
                    "delta": null,
                    "gamma": null,
                    "vega": null,
                    "price": 6.38450003
                },
                {
                    "contract_localSymbol": "FISV  260508C00058000",
                    "contract_strike": 58.0,
                    "contract_right": "C",
                    "Bid": -1.0,
                    "Ask": -1.0,
                    "IV": null,
                    "call_open_interest": 22.0,
                    "put_open_interest": 0.0,
                    "theta": null,
                    "delta": null,
                    "gamma": null,
                    "vega": null,
                    "price": 5.67088985
                },
                {
                    "contract_localSymbol": "FISV  260508C00059000",
                    "contract_strike": 59.0,
                    "contract_right": "C",
                    "Bid": -1.0,
                    "Ask": -1.0,
                    "IV": null,
                    "call_open_interest": 18.0,
                    "put_open_interest": 0.0,
                    "theta": null,
                    "delta": null,
                    "gamma": null,
                    "vega": null,
                    "price": 5.00991011
                },
                {
                    "contract_localSymbol": "FISV  260508C00060000",
                    "contract_strike": 60.0,
                    "contract_right": "C",
                    "Bid": -1.0,
                    "Ask": -1.0,
                    "IV": null,
                    "call_open_interest": 258.0,
                    "put_open_interest": 0.0,
                    "theta": null,
                    "delta": null,
                    "gamma": null,
                    "vega": null,
                    "price": 4.40560007
                },
                {
                    "contract_localSymbol": "FISV  260508C00061000",
                    "contract_strike": 61.0,
                    "contract_right": "C",
                    "Bid": -1.0,
                    "Ask": -1.0,
                    "IV": null,
                    "call_open_interest": 73.0,
                    "put_open_interest": 0.0,
                    "theta": null,
                    "delta": null,
                    "gamma": null,
                    "vega": null,
                    "price": 3.82379007
                },
                {
                    "contract_localSymbol": "FISV  260508C00062000",
                    "contract_strike": 62.0,
                    "contract_right": "C",
                    "Bid": -1.0,
                    "Ask": -1.0,
                    "IV": null,
                    "call_open_interest": 128.0,
                    "put_open_interest": 0.0,
                    "theta": null,
                    "delta": null,
                    "gamma": null,
                    "vega": null,
                    "price": 3.34383988
                },
                {
                    "contract_localSymbol": "FISV  260508C00063000",
                    "contract_strike": 63.0,
                    "contract_right": "C",
                    "Bid": -1.0,
                    "Ask": -1.0,
                    "IV": null,
                    "call_open_interest": 198.0,
                    "put_open_interest": 0.0,
                    "theta": null,
                    "delta": null,
                    "gamma": null,
                    "vega": null,
                    "price": 2.87196994
                },
                {
                    "contract_localSymbol": "FISV  260508C00064000",
                    "contract_strike": 64.0,
                    "contract_right": "C",
                    "Bid": -1.0,
                    "Ask": -1.0,
                    "IV": null,
                    "call_open_interest": 228.0,
                    "put_open_interest": 0.0,
                    "theta": null,
                    "delta": null,
                    "gamma": null,
                    "vega": null,
                    "price": 2.44634008
                },
                {
                    "contract_localSymbol": "FISV  260508P00062000",
                    "contract_strike": 62.0,
                    "contract_right": "P",
                    "Bid": -1.0,
                    "Ask": -1.0,
                    "IV": null,
                    "call_open_interest": 0.0,
                    "put_open_interest": 149.0,
                    "theta": null,
                    "delta": null,
                    "gamma": null,
                    "vega": null,
                    "price": 3.0564301
                },
                {
                    "contract_localSymbol": "FISV  260508P00061500",
                    "contract_strike": 61.5,
                    "contract_right": "P",
                    "Bid": -1.0,
                    "Ask": -1.0,
                    "IV": null,
                    "call_open_interest": 0.0,
                    "put_open_interest": 159.0,
                    "theta": null,
                    "delta": null,
                    "gamma": null,
                    "vega": null,
                    "price": 2.83853006
                }
            ],
            "recommendation": {
                "expected_move": 6.05538499,
                "average_percent_move": 9.573587724627581,
                "lower_boundary": 50.49923063,
                "upper_boundary": 74.72077059
            }
        },
        {
            "timestamp": "2026-05-04 09:48:40",
            "underlying_prices": {
                "Bid": 62.95,
                "Ask": 63.0,
                "get_instrument_value": 62.97999954
            },
            "option_prices": [
                {
                    "contract_localSymbol": "FISV  260508C00063000",
                    "contract_strike": 63.0,
                    "contract_right": "C",
                    "Bid": 2.85,
                    "Ask": 3.4,
                    "IV": null,
                    "call_open_interest": 227.0,
                    "put_open_interest": 0.0,
                    "theta": null,
                    "delta": null,
                    "gamma": null,
                    "vega": null,
                    "price": 3.1500000953674316
                },
                {
                    "contract_localSymbol": "FISV  260508C00050000",
                    "contract_strike": 50.0,
                    "contract_right": "C",
                    "Bid": 11.6,
                    "Ask": 13.7,
                    "IV": null,
                    "call_open_interest": null,
                    "put_open_interest": null,
                    "theta": null,
                    "delta": null,
                    "gamma": null,
                    "vega": null,
                    "price": 13.11888599
                },
                {
                    "contract_localSymbol": "FISV  260508C00051000",
                    "contract_strike": 51.0,
                    "contract_right": "C",
                    "Bid": 10.5,
                    "Ask": 12.7,
                    "IV": null,
                    "call_open_interest": null,
                    "put_open_interest": null,
                    "theta": null,
                    "delta": null,
                    "gamma": null,
                    "vega": null,
                    "price": 12.15731144
                },
                {
                    "contract_localSymbol": "FISV  260508C00052000",
                    "contract_strike": 52.0,
                    "contract_right": "C",
                    "Bid": 10.0,
                    "Ask": 11.9,
                    "IV": null,
                    "call_open_interest": null,
                    "put_open_interest": null,
                    "theta": null,
                    "delta": null,
                    "gamma": null,
                    "vega": null,
                    "price": 11.21459293
                },
                {
                    "contract_localSymbol": "FISV  260508C00053000",
                    "contract_strike": 53.0,
                    "contract_right": "C",
                    "Bid": 8.7,
                    "Ask": 10.9,
                    "IV": null,
                    "call_open_interest": null,
                    "put_open_interest": null,
                    "theta": null,
                    "delta": null,
                    "gamma": null,
                    "vega": null,
                    "price": 10.26850796
                },
                {
                    "contract_localSymbol": "FISV  260508C00054000",
                    "contract_strike": 54.0,
                    "contract_right": "C",
                    "Bid": 8.2,
                    "Ask": 10.1,
                    "IV": null,
                    "call_open_interest": null,
                    "put_open_interest": null,
                    "theta": null,
                    "delta": null,
                    "gamma": null,
                    "vega": null,
                    "price": 9.37395477
                },
                {
                    "contract_localSymbol": "FISV  260508C00055000",
                    "contract_strike": 55.0,
                    "contract_right": "C",
                    "Bid": 7.2,
                    "Ask": 9.1,
                    "IV": null,
                    "call_open_interest": null,
                    "put_open_interest": null,
                    "theta": null,
                    "delta": null,
                    "gamma": null,
                    "vega": null,
                    "price": 8.53035545
                },
                {
                    "contract_localSymbol": "FISV  260508C00056000",
                    "contract_strike": 56.0,
                    "contract_right": "C",
                    "Bid": 6.4,
                    "Ask": 8.4,
                    "IV": null,
                    "call_open_interest": null,
                    "put_open_interest": null,
                    "theta": null,
                    "delta": null,
                    "gamma": null,
                    "vega": null,
                    "price": 8.399999618530273
                },
                {
                    "contract_localSymbol": "FISV  260508C00057000",
                    "contract_strike": 57.0,
                    "contract_right": "C",
                    "Bid": 5.9,
                    "Ask": 7.3,
                    "IV": null,
                    "call_open_interest": null,
                    "put_open_interest": null,
                    "theta": null,
                    "delta": null,
                    "gamma": null,
                    "vega": null,
                    "price": 7.300000190734863
                },
                {
                    "contract_localSymbol": "FISV  260508C00058000",
                    "contract_strike": 58.0,
                    "contract_right": "C",
                    "Bid": 5.2,
                    "Ask": 6.6,
                    "IV": null,
                    "call_open_interest": null,
                    "put_open_interest": null,
                    "theta": null,
                    "delta": null,
                    "gamma": null,
                    "vega": null,
                    "price": 6.599999904632568
                },
                {
                    "contract_localSymbol": "FISV  260508C00059000",
                    "contract_strike": 59.0,
                    "contract_right": "C",
                    "Bid": 4.5,
                    "Ask": 5.9,
                    "IV": null,
                    "call_open_interest": 21.0,
                    "put_open_interest": 0.0,
                    "theta": null,
                    "delta": null,
                    "gamma": null,
                    "vega": null,
                    "price": 5.900000095367432
                },
                {
                    "contract_localSymbol": "FISV  260508C00060000",
                    "contract_strike": 60.0,
                    "contract_right": "C",
                    "Bid": 4.0,
                    "Ask": 5.2,
                    "IV": null,
                    "call_open_interest": null,
                    "put_open_interest": null,
                    "theta": null,
                    "delta": null,
                    "gamma": null,
                    "vega": null,
                    "price": 5.199999809265137
                },
                {
                    "contract_localSymbol": "FISV  260508C00061000",
                    "contract_strike": 61.0,
                    "contract_right": "C",
                    "Bid": 3.7,
                    "Ask": 4.6,
                    "IV": null,
                    "call_open_interest": null,
                    "put_open_interest": null,
                    "theta": null,
                    "delta": null,
                    "gamma": null,
                    "vega": null,
                    "price": 4.599999904632568
                },
                {
                    "contract_localSymbol": "FISV  260508C00062000",
                    "contract_strike": 62.0,
                    "contract_right": "C",
                    "Bid": 3.3,
                    "Ask": 4.2,
                    "IV": 1.2159108434582537,
                    "call_open_interest": 166.0,
                    "put_open_interest": 0.0,
                    "theta": -0.385037143521281,
                    "delta": 0.5767152966095823,
                    "gamma": 0.047434547907993174,
                    "vega": 0.02679173916978339,
                    "price": 3.5
                },
                {
                    "contract_localSymbol": "FISV  260508P00073000",
                    "contract_strike": 73.0,
                    "contract_right": "P",
                    "Bid": 9.9,
                    "Ask": 12.1,
                    "IV": null,
                    "call_open_interest": null,
                    "put_open_interest": null,
                    "theta": null,
                    "delta": null,
                    "gamma": null,
                    "vega": null,
                    "price": 10.47427082
                },
                {
                    "contract_localSymbol": "FISV  260508C00064000",
                    "contract_strike": 64.0,
                    "contract_right": "C",
                    "Bid": 2.15,
                    "Ask": 2.9,
                    "IV": 1.3329822685474337,
                    "call_open_interest": 239.0,
                    "put_open_interest": 0.0,
                    "theta": -0.428810117373128,
                    "delta": 0.4873102046383902,
                    "gamma": 0.044050365880201454,
                    "vega": 0.027229143288745483,
                    "price": 3.0
                },
                {
                    "contract_localSymbol": "FISV  260508P00062000",
                    "contract_strike": 62.0,
                    "contract_right": "P",
                    "Bid": 2.6,
                    "Ask": 2.9,
                    "IV": 1.2162523577381161,
                    "call_open_interest": 0.0,
                    "put_open_interest": 161.0,
                    "theta": -0.3788212153282775,
                    "delta": -0.4235077777215126,
                    "gamma": 0.04745653747139403,
                    "vega": 0.026792471949114383,
                    "price": 3.0
                },
                {
                    "contract_localSymbol": "FISV  260508P00061500",
                    "contract_strike": 61.5,
                    "contract_right": "P",
                    "Bid": 2.25,
                    "Ask": 3.3,
                    "IV": 1.0810879976132726,
                    "call_open_interest": 0.0,
                    "put_open_interest": 159.0,
                    "theta": -0.3318278703607679,
                    "delta": -0.393070642467656,
                    "gamma": 0.05263405094779025,
                    "vega": 0.025647886063892678,
                    "price": 2.200000047683716
                }
            ],
            "recommendation": {
                "expected_move": 6.019631625,
                "average_percent_move": 9.573587724627581,
                "lower_boundary": 50.940736290000004,
                "upper_boundary": 75.01926279
            }
        }
    ],
    "historic_move": [
        {
            "date": "20250515",
            "open": 189.32,
            "high": 190.86,
            "low": 157.35,
            "close": 159.13,
            "candle_length": 33.51000000000002,
            "percent_move": 21.05825425752531
        },
        {
            "date": "20251029",
            "open": 71.36,
            "high": 76.65,
            "low": 66.58,
            "close": 70.6,
            "candle_length": 10.070000000000007,
            "percent_move": 14.26345609065157
        },
        {
            "date": "20250424",
            "open": 195.39,
            "high": 198.68,
            "low": 176.24,
            "close": 176.9,
            "candle_length": 22.439999999999998,
            "percent_move": 12.685132843414356
        },
        {
            "date": "20250723",
            "open": 137.0,
            "high": 143.25,
            "low": 128.22,
            "close": 143.0,
            "candle_length": 15.030000000000001,
            "percent_move": 10.510489510489512
        },
        {
            "date": "20250409",
            "open": 192.17,
            "high": 211.63,
            "low": 191.11,
            "close": 210.38,
            "candle_length": 20.519999999999982,
            "percent_move": 9.753778876319034
        },
        {
            "date": "20250408",
            "open": 206.56,
            "high": 208.2,
            "low": 191.44,
            "close": 195.59,
            "candle_length": 16.75999999999999,
            "percent_move": 8.56894524259931
        },
        {
            "date": "20251030",
            "open": 68.87,
            "high": 70.1,
            "low": 64.52,
            "close": 65.19,
            "candle_length": 5.579999999999998,
            "percent_move": 8.559595029912561
        },
        {
            "date": "20250407",
            "open": 192.2,
            "high": 202.85,
            "low": 186.66,
            "close": 198.44,
            "candle_length": 16.189999999999998,
            "percent_move": 8.158637371497681
        },
        {
            "date": "20260210",
            "open": 59.64,
            "high": 63.59,
            "low": 58.62,
            "close": 62.59,
            "candle_length": 4.970000000000006,
            "percent_move": 7.940565585556807
        },
        {
            "date": "20260212",
            "open": 62.53,
            "high": 62.75,
            "low": 58.53,
            "close": 58.82,
            "candle_length": 4.219999999999999,
            "percent_move": 7.174430465827948
        },
        {
            "date": "20260203",
            "open": 61.29,
            "high": 61.79,
            "low": 57.79,
            "close": 58.12,
            "candle_length": 4.0,
            "percent_move": 6.882312456985547
        },
        {
            "date": "20250404",
            "open": 209.4,
            "high": 211.28,
            "low": 198.51,
            "close": 198.6,
            "candle_length": 12.77000000000001,
            "percent_move": 6.430010070493459
        },
        {
            "date": "20260225",
            "open": 59.63,
            "high": 62.86,
            "low": 58.95,
            "close": 61.61,
            "candle_length": 3.9099999999999966,
            "percent_move": 6.346372342152243
        },
        {
            "date": "20260413",
            "open": 55.81,
            "high": 59.05,
            "low": 55.7,
            "close": 58.79,
            "candle_length": 3.3499999999999943,
            "percent_move": 5.698248001360766
        }
    ]
}