{
    "prices": [
        {
            "timestamp": "2026-04-21 16:47:49",
            "underlying_prices": {
                "Bid": 100.94,
                "Ask": 101.0,
                "get_instrument_value": 101.0
            },
            "option_prices": [
                {
                    "contract_localSymbol": "NOW   260424C00100000",
                    "contract_strike": 100.0,
                    "contract_right": "C",
                    "Bid": -1.0,
                    "Ask": -1.0,
                    "IV": null,
                    "call_open_interest": 5554.0,
                    "put_open_interest": 0.0,
                    "theta": null,
                    "delta": null,
                    "gamma": null,
                    "vega": null,
                    "price": 5.19999981
                },
                {
                    "contract_localSymbol": "NOW   260424C00105000",
                    "contract_strike": 105.0,
                    "contract_right": "C",
                    "Bid": -1.0,
                    "Ask": -1.0,
                    "IV": null,
                    "call_open_interest": 1667.0,
                    "put_open_interest": 0.0,
                    "theta": null,
                    "delta": null,
                    "gamma": null,
                    "vega": null,
                    "price": 3.20000005
                },
                {
                    "contract_localSymbol": "NOW   260424C00110000",
                    "contract_strike": 110.0,
                    "contract_right": "C",
                    "Bid": -1.0,
                    "Ask": -1.0,
                    "IV": null,
                    "call_open_interest": 2260.0,
                    "put_open_interest": 0.0,
                    "theta": null,
                    "delta": null,
                    "gamma": null,
                    "vega": null,
                    "price": 1.89999998
                },
                {
                    "contract_localSymbol": "NOW   260424C00115000",
                    "contract_strike": 115.0,
                    "contract_right": "C",
                    "Bid": -1.0,
                    "Ask": -1.0,
                    "IV": null,
                    "call_open_interest": 1348.0,
                    "put_open_interest": 0.0,
                    "theta": null,
                    "delta": null,
                    "gamma": null,
                    "vega": null,
                    "price": 1.10000002
                },
                {
                    "contract_localSymbol": "NOW   260424C00120000",
                    "contract_strike": 120.0,
                    "contract_right": "C",
                    "Bid": -1.0,
                    "Ask": -1.0,
                    "IV": null,
                    "call_open_interest": 1528.0,
                    "put_open_interest": 0.0,
                    "theta": null,
                    "delta": null,
                    "gamma": null,
                    "vega": null,
                    "price": 0.64999998
                },
                {
                    "contract_localSymbol": "NOW   260424C00085000",
                    "contract_strike": 85.0,
                    "contract_right": "C",
                    "Bid": -1.0,
                    "Ask": -1.0,
                    "IV": null,
                    "call_open_interest": 1845.0,
                    "put_open_interest": 0.0,
                    "theta": null,
                    "delta": null,
                    "gamma": null,
                    "vega": null,
                    "price": 16.10000038
                },
                {
                    "contract_localSymbol": "NOW   260424C00090000",
                    "contract_strike": 90.0,
                    "contract_right": "C",
                    "Bid": -1.0,
                    "Ask": -1.0,
                    "IV": null,
                    "call_open_interest": 2095.0,
                    "put_open_interest": 0.0,
                    "theta": null,
                    "delta": null,
                    "gamma": null,
                    "vega": null,
                    "price": 12.05204487
                },
                {
                    "contract_localSymbol": "NOW   260424C00095000",
                    "contract_strike": 95.0,
                    "contract_right": "C",
                    "Bid": -1.0,
                    "Ask": -1.0,
                    "IV": null,
                    "call_open_interest": 1630.0,
                    "put_open_interest": 0.0,
                    "theta": null,
                    "delta": null,
                    "gamma": null,
                    "vega": null,
                    "price": 7.9000001
                },
                {
                    "contract_localSymbol": "NOW   260424P00100000",
                    "contract_strike": 100.0,
                    "contract_right": "P",
                    "Bid": -1.0,
                    "Ask": -1.0,
                    "IV": null,
                    "call_open_interest": 0.0,
                    "put_open_interest": 1214.0,
                    "theta": null,
                    "delta": null,
                    "gamma": null,
                    "vega": null,
                    "price": 4.80000019
                },
                {
                    "contract_localSymbol": "NOW   260424P00105000",
                    "contract_strike": 105.0,
                    "contract_right": "P",
                    "Bid": -1.0,
                    "Ask": -1.0,
                    "IV": null,
                    "call_open_interest": 0.0,
                    "put_open_interest": 278.0,
                    "theta": null,
                    "delta": null,
                    "gamma": null,
                    "vega": null,
                    "price": 7.5999999
                },
                {
                    "contract_localSymbol": "NOW   260424P00110000",
                    "contract_strike": 110.0,
                    "contract_right": "P",
                    "Bid": -1.0,
                    "Ask": -1.0,
                    "IV": null,
                    "call_open_interest": 0.0,
                    "put_open_interest": 403.0,
                    "theta": null,
                    "delta": null,
                    "gamma": null,
                    "vega": null,
                    "price": 11.19999981
                },
                {
                    "contract_localSymbol": "NOW   260424P00115000",
                    "contract_strike": 115.0,
                    "contract_right": "P",
                    "Bid": -1.0,
                    "Ask": -1.0,
                    "IV": null,
                    "call_open_interest": 0.0,
                    "put_open_interest": 265.0,
                    "theta": null,
                    "delta": null,
                    "gamma": null,
                    "vega": null,
                    "price": 15.20352745
                },
                {
                    "contract_localSymbol": "NOW   260424P00120000",
                    "contract_strike": 120.0,
                    "contract_right": "P",
                    "Bid": -1.0,
                    "Ask": -1.0,
                    "IV": null,
                    "call_open_interest": 0.0,
                    "put_open_interest": 111.0,
                    "theta": null,
                    "delta": null,
                    "gamma": null,
                    "vega": null,
                    "price": 19.89999962
                },
                {
                    "contract_localSymbol": "NOW   260424P00085000",
                    "contract_strike": 85.0,
                    "contract_right": "P",
                    "Bid": -1.0,
                    "Ask": -1.0,
                    "IV": null,
                    "call_open_interest": 0.0,
                    "put_open_interest": 9739.0,
                    "theta": null,
                    "delta": null,
                    "gamma": null,
                    "vega": null,
                    "price": 0.40000001
                },
                {
                    "contract_localSymbol": "NOW   260424C00102000",
                    "contract_strike": 102.0,
                    "contract_right": "C",
                    "Bid": -1.0,
                    "Ask": -1.0,
                    "IV": null,
                    "call_open_interest": 1501.0,
                    "put_open_interest": 0.0,
                    "theta": null,
                    "delta": null,
                    "gamma": null,
                    "vega": null,
                    "price": 4.4000001
                },
                {
                    "contract_localSymbol": "NOW   260424C00104000",
                    "contract_strike": 104.0,
                    "contract_right": "C",
                    "Bid": -1.0,
                    "Ask": -1.0,
                    "IV": null,
                    "call_open_interest": 334.0,
                    "put_open_interest": 0.0,
                    "theta": null,
                    "delta": null,
                    "gamma": null,
                    "vega": null,
                    "price": -1.0
                },
                {
                    "contract_localSymbol": "NOW   260424P00090000",
                    "contract_strike": 90.0,
                    "contract_right": "P",
                    "Bid": -1.0,
                    "Ask": -1.0,
                    "IV": null,
                    "call_open_interest": 0.0,
                    "put_open_interest": 1434.0,
                    "theta": null,
                    "delta": null,
                    "gamma": null,
                    "vega": null,
                    "price": 1.10000002
                },
                {
                    "contract_localSymbol": "NOW   260424P00089000",
                    "contract_strike": 89.0,
                    "contract_right": "P",
                    "Bid": -1.0,
                    "Ask": -1.0,
                    "IV": null,
                    "call_open_interest": null,
                    "put_open_interest": null,
                    "theta": null,
                    "delta": null,
                    "gamma": null,
                    "vega": null,
                    "price": -1.0
                },
                {
                    "contract_localSymbol": "NOW   260424P00095000",
                    "contract_strike": 95.0,
                    "contract_right": "P",
                    "Bid": -1.0,
                    "Ask": -1.0,
                    "IV": null,
                    "call_open_interest": null,
                    "put_open_interest": null,
                    "theta": null,
                    "delta": null,
                    "gamma": null,
                    "vega": null,
                    "price": 2.5
                },
                {
                    "contract_localSymbol": "NOW   260424C00101000",
                    "contract_strike": 101.0,
                    "contract_right": "C",
                    "Bid": -1.0,
                    "Ask": -1.0,
                    "IV": null,
                    "call_open_interest": 463.0,
                    "put_open_interest": 0.0,
                    "theta": null,
                    "delta": null,
                    "gamma": null,
                    "vega": null,
                    "price": 4.80000019
                },
                {
                    "contract_localSymbol": "NOW   260424C00103000",
                    "contract_strike": 103.0,
                    "contract_right": "C",
                    "Bid": -1.0,
                    "Ask": -1.0,
                    "IV": null,
                    "call_open_interest": null,
                    "put_open_interest": null,
                    "theta": null,
                    "delta": null,
                    "gamma": null,
                    "vega": null,
                    "price": 4.0
                },
                {
                    "contract_localSymbol": "NOW   260424C00106000",
                    "contract_strike": 106.0,
                    "contract_right": "C",
                    "Bid": -1.0,
                    "Ask": -1.0,
                    "IV": null,
                    "call_open_interest": null,
                    "put_open_interest": null,
                    "theta": null,
                    "delta": null,
                    "gamma": null,
                    "vega": null,
                    "price": 2.95000005
                },
                {
                    "contract_localSymbol": "NOW   260424C00107000",
                    "contract_strike": 107.0,
                    "contract_right": "C",
                    "Bid": -1.0,
                    "Ask": -1.0,
                    "IV": null,
                    "call_open_interest": null,
                    "put_open_interest": null,
                    "theta": null,
                    "delta": null,
                    "gamma": null,
                    "vega": null,
                    "price": 2.6500001
                },
                {
                    "contract_localSymbol": "NOW   260424C00108000",
                    "contract_strike": 108.0,
                    "contract_right": "C",
                    "Bid": -1.0,
                    "Ask": -1.0,
                    "IV": null,
                    "call_open_interest": null,
                    "put_open_interest": null,
                    "theta": null,
                    "delta": null,
                    "gamma": null,
                    "vega": null,
                    "price": 2.4000001
                },
                {
                    "contract_localSymbol": "NOW   260424C00109000",
                    "contract_strike": 109.0,
                    "contract_right": "C",
                    "Bid": -1.0,
                    "Ask": -1.0,
                    "IV": null,
                    "call_open_interest": null,
                    "put_open_interest": null,
                    "theta": null,
                    "delta": null,
                    "gamma": null,
                    "vega": null,
                    "price": 2.29999995
                },
                {
                    "contract_localSymbol": "NOW   260424C00111000",
                    "contract_strike": 111.0,
                    "contract_right": "C",
                    "Bid": -1.0,
                    "Ask": -1.0,
                    "IV": null,
                    "call_open_interest": null,
                    "put_open_interest": null,
                    "theta": null,
                    "delta": null,
                    "gamma": null,
                    "vega": null,
                    "price": 1.79999995
                },
                {
                    "contract_localSymbol": "NOW   260424C00112000",
                    "contract_strike": 112.0,
                    "contract_right": "C",
                    "Bid": -1.0,
                    "Ask": -1.0,
                    "IV": null,
                    "call_open_interest": null,
                    "put_open_interest": null,
                    "theta": null,
                    "delta": null,
                    "gamma": null,
                    "vega": null,
                    "price": 1.69904602
                },
                {
                    "contract_localSymbol": "NOW   260424C00113000",
                    "contract_strike": 113.0,
                    "contract_right": "C",
                    "Bid": -1.0,
                    "Ask": -1.0,
                    "IV": null,
                    "call_open_interest": null,
                    "put_open_interest": null,
                    "theta": null,
                    "delta": null,
                    "gamma": null,
                    "vega": null,
                    "price": 1.45000005
                },
                {
                    "contract_localSymbol": "NOW   260424C00114000",
                    "contract_strike": 114.0,
                    "contract_right": "C",
                    "Bid": -1.0,
                    "Ask": -1.0,
                    "IV": null,
                    "call_open_interest": 200.0,
                    "put_open_interest": 0.0,
                    "theta": null,
                    "delta": null,
                    "gamma": null,
                    "vega": null,
                    "price": 1.39065111
                },
                {
                    "contract_localSymbol": "NOW   260424C00116000",
                    "contract_strike": 116.0,
                    "contract_right": "C",
                    "Bid": -1.0,
                    "Ask": -1.0,
                    "IV": null,
                    "call_open_interest": 189.0,
                    "put_open_interest": 0.0,
                    "theta": null,
                    "delta": null,
                    "gamma": null,
                    "vega": null,
                    "price": 1.0
                },
                {
                    "contract_localSymbol": "NOW   260424C00117000",
                    "contract_strike": 117.0,
                    "contract_right": "C",
                    "Bid": -1.0,
                    "Ask": -1.0,
                    "IV": null,
                    "call_open_interest": 84.0,
                    "put_open_interest": 0.0,
                    "theta": null,
                    "delta": null,
                    "gamma": null,
                    "vega": null,
                    "price": 1.0
                },
                {
                    "contract_localSymbol": "NOW   260424C00118000",
                    "contract_strike": 118.0,
                    "contract_right": "C",
                    "Bid": -1.0,
                    "Ask": -1.0,
                    "IV": null,
                    "call_open_interest": 21.0,
                    "put_open_interest": 0.0,
                    "theta": null,
                    "delta": null,
                    "gamma": null,
                    "vega": null,
                    "price": 0.85000002
                },
                {
                    "contract_localSymbol": "NOW   260424C00091000",
                    "contract_strike": 91.0,
                    "contract_right": "C",
                    "Bid": -1.0,
                    "Ask": -1.0,
                    "IV": null,
                    "call_open_interest": 277.0,
                    "put_open_interest": 0.0,
                    "theta": null,
                    "delta": null,
                    "gamma": null,
                    "vega": null,
                    "price": 11.25432301
                },
                {
                    "contract_localSymbol": "NOW   260424C00092000",
                    "contract_strike": 92.0,
                    "contract_right": "C",
                    "Bid": -1.0,
                    "Ask": -1.0,
                    "IV": null,
                    "call_open_interest": 218.0,
                    "put_open_interest": 0.0,
                    "theta": null,
                    "delta": null,
                    "gamma": null,
                    "vega": null,
                    "price": 10.47663689
                },
                {
                    "contract_localSymbol": "NOW   260424C00093000",
                    "contract_strike": 93.0,
                    "contract_right": "C",
                    "Bid": -1.0,
                    "Ask": -1.0,
                    "IV": null,
                    "call_open_interest": 383.0,
                    "put_open_interest": 0.0,
                    "theta": null,
                    "delta": null,
                    "gamma": null,
                    "vega": null,
                    "price": 9.5
                },
                {
                    "contract_localSymbol": "NOW   260424C00094000",
                    "contract_strike": 94.0,
                    "contract_right": "C",
                    "Bid": -1.0,
                    "Ask": -1.0,
                    "IV": null,
                    "call_open_interest": null,
                    "put_open_interest": null,
                    "theta": null,
                    "delta": null,
                    "gamma": null,
                    "vega": null,
                    "price": -1.0
                },
                {
                    "contract_localSymbol": "NOW   260424C00096000",
                    "contract_strike": 96.0,
                    "contract_right": "C",
                    "Bid": -1.0,
                    "Ask": -1.0,
                    "IV": null,
                    "call_open_interest": 647.0,
                    "put_open_interest": 0.0,
                    "theta": null,
                    "delta": null,
                    "gamma": null,
                    "vega": null,
                    "price": 7.4000001
                },
                {
                    "contract_localSymbol": "NOW   260424C00097000",
                    "contract_strike": 97.0,
                    "contract_right": "C",
                    "Bid": -1.0,
                    "Ask": -1.0,
                    "IV": null,
                    "call_open_interest": 595.0,
                    "put_open_interest": 0.0,
                    "theta": null,
                    "delta": null,
                    "gamma": null,
                    "vega": null,
                    "price": 6.80000019
                },
                {
                    "contract_localSymbol": "NOW   260424C00098000",
                    "contract_strike": 98.0,
                    "contract_right": "C",
                    "Bid": -1.0,
                    "Ask": -1.0,
                    "IV": null,
                    "call_open_interest": 765.0,
                    "put_open_interest": 0.0,
                    "theta": null,
                    "delta": null,
                    "gamma": null,
                    "vega": null,
                    "price": 6.30000019
                },
                {
                    "contract_localSymbol": "NOW   260424C00099000",
                    "contract_strike": 99.0,
                    "contract_right": "C",
                    "Bid": -1.0,
                    "Ask": -1.0,
                    "IV": null,
                    "call_open_interest": 209.0,
                    "put_open_interest": 0.0,
                    "theta": null,
                    "delta": null,
                    "gamma": null,
                    "vega": null,
                    "price": 5.80000019
                },
                {
                    "contract_localSymbol": "NOW   260424P00101000",
                    "contract_strike": 101.0,
                    "contract_right": "P",
                    "Bid": -1.0,
                    "Ask": -1.0,
                    "IV": null,
                    "call_open_interest": 0.0,
                    "put_open_interest": 111.0,
                    "theta": null,
                    "delta": null,
                    "gamma": null,
                    "vega": null,
                    "price": 5.19999981
                },
                {
                    "contract_localSymbol": "NOW   260424P00102000",
                    "contract_strike": 102.0,
                    "contract_right": "P",
                    "Bid": -1.0,
                    "Ask": -1.0,
                    "IV": null,
                    "call_open_interest": null,
                    "put_open_interest": null,
                    "theta": null,
                    "delta": null,
                    "gamma": null,
                    "vega": null,
                    "price": -1.0
                },
                {
                    "contract_localSymbol": "NOW   260424P00103000",
                    "contract_strike": 103.0,
                    "contract_right": "P",
                    "Bid": -1.0,
                    "Ask": -1.0,
                    "IV": null,
                    "call_open_interest": 0.0,
                    "put_open_interest": 77.0,
                    "theta": null,
                    "delta": null,
                    "gamma": null,
                    "vega": null,
                    "price": 6.19999981
                },
                {
                    "contract_localSymbol": "NOW   260424P00104000",
                    "contract_strike": 104.0,
                    "contract_right": "P",
                    "Bid": -1.0,
                    "Ask": -1.0,
                    "IV": null,
                    "call_open_interest": 0.0,
                    "put_open_interest": 43.0,
                    "theta": null,
                    "delta": null,
                    "gamma": null,
                    "vega": null,
                    "price": 6.9000001
                },
                {
                    "contract_localSymbol": "NOW   260424P00106000",
                    "contract_strike": 106.0,
                    "contract_right": "P",
                    "Bid": -1.0,
                    "Ask": -1.0,
                    "IV": null,
                    "call_open_interest": 0.0,
                    "put_open_interest": 8.0,
                    "theta": null,
                    "delta": null,
                    "gamma": null,
                    "vega": null,
                    "price": 8.30000019
                },
                {
                    "contract_localSymbol": "NOW   260424P00107000",
                    "contract_strike": 107.0,
                    "contract_right": "P",
                    "Bid": -1.0,
                    "Ask": -1.0,
                    "IV": null,
                    "call_open_interest": 0.0,
                    "put_open_interest": 26.0,
                    "theta": null,
                    "delta": null,
                    "gamma": null,
                    "vega": null,
                    "price": 8.81260109
                },
                {
                    "contract_localSymbol": "NOW   260424P00108000",
                    "contract_strike": 108.0,
                    "contract_right": "P",
                    "Bid": -1.0,
                    "Ask": -1.0,
                    "IV": null,
                    "call_open_interest": 0.0,
                    "put_open_interest": 54.0,
                    "theta": null,
                    "delta": null,
                    "gamma": null,
                    "vega": null,
                    "price": 9.54618454
                },
                {
                    "contract_localSymbol": "NOW   260424P00109000",
                    "contract_strike": 109.0,
                    "contract_right": "P",
                    "Bid": -1.0,
                    "Ask": -1.0,
                    "IV": null,
                    "call_open_interest": 0.0,
                    "put_open_interest": 69.0,
                    "theta": null,
                    "delta": null,
                    "gamma": null,
                    "vega": null,
                    "price": 10.30000019
                },
                {
                    "contract_localSymbol": "NOW   260424P00111000",
                    "contract_strike": 111.0,
                    "contract_right": "P",
                    "Bid": -1.0,
                    "Ask": -1.0,
                    "IV": null,
                    "call_open_interest": 0.0,
                    "put_open_interest": 5.0,
                    "theta": null,
                    "delta": null,
                    "gamma": null,
                    "vega": null,
                    "price": 11.86381721
                },
                {
                    "contract_localSymbol": "NOW   260424P00112000",
                    "contract_strike": 112.0,
                    "contract_right": "P",
                    "Bid": -1.0,
                    "Ask": -1.0,
                    "IV": null,
                    "call_open_interest": 0.0,
                    "put_open_interest": 0.0,
                    "theta": null,
                    "delta": null,
                    "gamma": null,
                    "vega": null,
                    "price": 12.66096878
                },
                {
                    "contract_localSymbol": "NOW   260424P00113000",
                    "contract_strike": 113.0,
                    "contract_right": "P",
                    "Bid": -1.0,
                    "Ask": -1.0,
                    "IV": null,
                    "call_open_interest": 0.0,
                    "put_open_interest": 57.0,
                    "theta": null,
                    "delta": null,
                    "gamma": null,
                    "vega": null,
                    "price": 13.50217247
                },
                {
                    "contract_localSymbol": "NOW   260424P00114000",
                    "contract_strike": 114.0,
                    "contract_right": "P",
                    "Bid": -1.0,
                    "Ask": -1.0,
                    "IV": null,
                    "call_open_interest": 0.0,
                    "put_open_interest": 6.0,
                    "theta": null,
                    "delta": null,
                    "gamma": null,
                    "vega": null,
                    "price": 14.5
                },
                {
                    "contract_localSymbol": "NOW   260424P00116000",
                    "contract_strike": 116.0,
                    "contract_right": "P",
                    "Bid": -1.0,
                    "Ask": -1.0,
                    "IV": null,
                    "call_open_interest": 0.0,
                    "put_open_interest": 1.0,
                    "theta": null,
                    "delta": null,
                    "gamma": null,
                    "vega": null,
                    "price": 16.08046341
                },
                {
                    "contract_localSymbol": "NOW   260424P00117000",
                    "contract_strike": 117.0,
                    "contract_right": "P",
                    "Bid": -1.0,
                    "Ask": -1.0,
                    "IV": null,
                    "call_open_interest": 0.0,
                    "put_open_interest": 0.0,
                    "theta": null,
                    "delta": null,
                    "gamma": null,
                    "vega": null,
                    "price": 16.97393417
                },
                {
                    "contract_localSymbol": "NOW   260424P00118000",
                    "contract_strike": 118.0,
                    "contract_right": "P",
                    "Bid": -1.0,
                    "Ask": -1.0,
                    "IV": null,
                    "call_open_interest": 0.0,
                    "put_open_interest": 68.0,
                    "theta": null,
                    "delta": null,
                    "gamma": null,
                    "vega": null,
                    "price": 17.87025452
                },
                {
                    "contract_localSymbol": "NOW   260424P00091000",
                    "contract_strike": 91.0,
                    "contract_right": "P",
                    "Bid": -1.0,
                    "Ask": -1.0,
                    "IV": null,
                    "call_open_interest": 0.0,
                    "put_open_interest": 176.0,
                    "theta": null,
                    "delta": null,
                    "gamma": null,
                    "vega": null,
                    "price": 1.25
                },
                {
                    "contract_localSymbol": "NOW   260424P00092000",
                    "contract_strike": 92.0,
                    "contract_right": "P",
                    "Bid": -1.0,
                    "Ask": -1.0,
                    "IV": null,
                    "call_open_interest": 0.0,
                    "put_open_interest": 375.0,
                    "theta": null,
                    "delta": null,
                    "gamma": null,
                    "vega": null,
                    "price": 1.62073731
                },
                {
                    "contract_localSymbol": "NOW   260424P00093000",
                    "contract_strike": 93.0,
                    "contract_right": "P",
                    "Bid": -1.0,
                    "Ask": -1.0,
                    "IV": null,
                    "call_open_interest": 0.0,
                    "put_open_interest": 277.0,
                    "theta": null,
                    "delta": null,
                    "gamma": null,
                    "vega": null,
                    "price": 1.70771945
                },
                {
                    "contract_localSymbol": "NOW   260424P00094000",
                    "contract_strike": 94.0,
                    "contract_right": "P",
                    "Bid": -1.0,
                    "Ask": -1.0,
                    "IV": null,
                    "call_open_interest": 0.0,
                    "put_open_interest": 294.0,
                    "theta": null,
                    "delta": null,
                    "gamma": null,
                    "vega": null,
                    "price": 2.21446013
                },
                {
                    "contract_localSymbol": "NOW   260424P00096000",
                    "contract_strike": 96.0,
                    "contract_right": "P",
                    "Bid": -1.0,
                    "Ask": -1.0,
                    "IV": null,
                    "call_open_interest": 0.0,
                    "put_open_interest": 325.0,
                    "theta": null,
                    "delta": null,
                    "gamma": null,
                    "vega": null,
                    "price": 2.8499999
                },
                {
                    "contract_localSymbol": "NOW   260424P00097000",
                    "contract_strike": 97.0,
                    "contract_right": "P",
                    "Bid": -1.0,
                    "Ask": -1.0,
                    "IV": null,
                    "call_open_interest": 0.0,
                    "put_open_interest": 176.0,
                    "theta": null,
                    "delta": null,
                    "gamma": null,
                    "vega": null,
                    "price": 3.0999999
                },
                {
                    "contract_localSymbol": "NOW   260424P00098000",
                    "contract_strike": 98.0,
                    "contract_right": "P",
                    "Bid": -1.0,
                    "Ask": -1.0,
                    "IV": null,
                    "call_open_interest": 0.0,
                    "put_open_interest": 91.0,
                    "theta": null,
                    "delta": null,
                    "gamma": null,
                    "vega": null,
                    "price": 3.70000005
                },
                {
                    "contract_localSymbol": "NOW   260424P00099000",
                    "contract_strike": 99.0,
                    "contract_right": "P",
                    "Bid": -1.0,
                    "Ask": -1.0,
                    "IV": null,
                    "call_open_interest": 0.0,
                    "put_open_interest": 58.0,
                    "theta": null,
                    "delta": null,
                    "gamma": null,
                    "vega": null,
                    "price": 4.19999981
                },
                {
                    "contract_localSymbol": "NOW   260424C00087000",
                    "contract_strike": 87.0,
                    "contract_right": "C",
                    "Bid": -1.0,
                    "Ask": -1.0,
                    "IV": null,
                    "call_open_interest": 64.0,
                    "put_open_interest": 0.0,
                    "theta": null,
                    "delta": null,
                    "gamma": null,
                    "vega": null,
                    "price": 14.60905933
                },
                {
                    "contract_localSymbol": "NOW   260424C00088000",
                    "contract_strike": 88.0,
                    "contract_right": "C",
                    "Bid": -1.0,
                    "Ask": -1.0,
                    "IV": null,
                    "call_open_interest": 482.0,
                    "put_open_interest": 0.0,
                    "theta": null,
                    "delta": null,
                    "gamma": null,
                    "vega": null,
                    "price": 13.7350111
                },
                {
                    "contract_localSymbol": "NOW   260424C00089000",
                    "contract_strike": 89.0,
                    "contract_right": "C",
                    "Bid": -1.0,
                    "Ask": -1.0,
                    "IV": null,
                    "call_open_interest": 91.0,
                    "put_open_interest": 0.0,
                    "theta": null,
                    "delta": null,
                    "gamma": null,
                    "vega": null,
                    "price": 12.88172913
                },
                {
                    "contract_localSymbol": "NOW   260424C00097500",
                    "contract_strike": 97.5,
                    "contract_right": "C",
                    "Bid": -1.0,
                    "Ask": -1.0,
                    "IV": null,
                    "call_open_interest": 182.0,
                    "put_open_interest": 0.0,
                    "theta": null,
                    "delta": null,
                    "gamma": null,
                    "vega": null,
                    "price": 6.5
                },
                {
                    "contract_localSymbol": "NOW   260424C00098500",
                    "contract_strike": 98.5,
                    "contract_right": "C",
                    "Bid": -1.0,
                    "Ask": -1.0,
                    "IV": null,
                    "call_open_interest": null,
                    "put_open_interest": null,
                    "theta": null,
                    "delta": null,
                    "gamma": null,
                    "vega": null,
                    "price": 6.0
                },
                {
                    "contract_localSymbol": "NOW   260424P00087000",
                    "contract_strike": 87.0,
                    "contract_right": "P",
                    "Bid": -1.0,
                    "Ask": -1.0,
                    "IV": null,
                    "call_open_interest": null,
                    "put_open_interest": null,
                    "theta": null,
                    "delta": null,
                    "gamma": null,
                    "vega": null,
                    "price": 0.60000002
                },
                {
                    "contract_localSymbol": "NOW   260424P00088000",
                    "contract_strike": 88.0,
                    "contract_right": "P",
                    "Bid": -1.0,
                    "Ask": -1.0,
                    "IV": null,
                    "call_open_interest": null,
                    "put_open_interest": null,
                    "theta": null,
                    "delta": null,
                    "gamma": null,
                    "vega": null,
                    "price": 0.80000001
                },
                {
                    "contract_localSymbol": "NOW   260424P00097500",
                    "contract_strike": 97.5,
                    "contract_right": "P",
                    "Bid": -1.0,
                    "Ask": -1.0,
                    "IV": null,
                    "call_open_interest": null,
                    "put_open_interest": null,
                    "theta": null,
                    "delta": null,
                    "gamma": null,
                    "vega": null,
                    "price": 3.5
                },
                {
                    "contract_localSymbol": "NOW   260424P00098500",
                    "contract_strike": 98.5,
                    "contract_right": "P",
                    "Bid": -1.0,
                    "Ask": -1.0,
                    "IV": null,
                    "call_open_interest": null,
                    "put_open_interest": null,
                    "theta": null,
                    "delta": null,
                    "gamma": null,
                    "vega": null,
                    "price": 3.9000001
                },
                {
                    "contract_localSymbol": "NOW   260424C00086000",
                    "contract_strike": 86.0,
                    "contract_right": "C",
                    "Bid": -1.0,
                    "Ask": -1.0,
                    "IV": null,
                    "call_open_interest": null,
                    "put_open_interest": null,
                    "theta": null,
                    "delta": null,
                    "gamma": null,
                    "vega": null,
                    "price": 15.39999962
                },
                {
                    "contract_localSymbol": "NOW   260424P00086000",
                    "contract_strike": 86.0,
                    "contract_right": "P",
                    "Bid": -1.0,
                    "Ask": -1.0,
                    "IV": null,
                    "call_open_interest": null,
                    "put_open_interest": null,
                    "theta": null,
                    "delta": null,
                    "gamma": null,
                    "vega": null,
                    "price": 0.45502785
                },
                {
                    "contract_localSymbol": "NOW   260424C00081500",
                    "contract_strike": 81.5,
                    "contract_right": "C",
                    "Bid": -1.0,
                    "Ask": -1.0,
                    "IV": null,
                    "call_open_interest": null,
                    "put_open_interest": null,
                    "theta": null,
                    "delta": null,
                    "gamma": null,
                    "vega": null,
                    "price": 19.7177906
                },
                {
                    "contract_localSymbol": "NOW   260424C00081000",
                    "contract_strike": 81.0,
                    "contract_right": "C",
                    "Bid": -1.0,
                    "Ask": -1.0,
                    "IV": null,
                    "call_open_interest": null,
                    "put_open_interest": null,
                    "theta": null,
                    "delta": null,
                    "gamma": null,
                    "vega": null,
                    "price": 20.20055771
                },
                {
                    "contract_localSymbol": "NOW   260424C00082500",
                    "contract_strike": 82.5,
                    "contract_right": "C",
                    "Bid": -1.0,
                    "Ask": -1.0,
                    "IV": null,
                    "call_open_interest": null,
                    "put_open_interest": null,
                    "theta": null,
                    "delta": null,
                    "gamma": null,
                    "vega": null,
                    "price": 18.76275635
                },
                {
                    "contract_localSymbol": "NOW   260424C00082000",
                    "contract_strike": 82.0,
                    "contract_right": "C",
                    "Bid": -1.0,
                    "Ask": -1.0,
                    "IV": null,
                    "call_open_interest": 22.0,
                    "put_open_interest": 0.0,
                    "theta": null,
                    "delta": null,
                    "gamma": null,
                    "vega": null,
                    "price": 19.23937988
                },
                {
                    "contract_localSymbol": "NOW   260424C00083500",
                    "contract_strike": 83.5,
                    "contract_right": "C",
                    "Bid": -1.0,
                    "Ask": -1.0,
                    "IV": null,
                    "call_open_interest": null,
                    "put_open_interest": null,
                    "theta": null,
                    "delta": null,
                    "gamma": null,
                    "vega": null,
                    "price": 17.81454277
                }
            ],
            "recommendation": {
                "expected_move": 9.600000145,
                "average_percent_move": 8.760942826693919,
                "lower_boundary": 81.79999971000001,
                "upper_boundary": 120.20000028999999
            }
        },
        {
            "timestamp": "2026-04-22 17:30:49",
            "underlying_prices": {
                "Bid": 103.16,
                "Ask": 103.2,
                "get_instrument_value": 103.18499756
            },
            "option_prices": [
                {
                    "contract_localSymbol": "NOW   260424C00100000",
                    "contract_strike": 100.0,
                    "contract_right": "C",
                    "Bid": 6.3,
                    "Ask": 6.5,
                    "IV": 1.5067812064414214,
                    "call_open_interest": 4909.0,
                    "put_open_interest": 0.0,
                    "theta": -1.0496945376547482,
                    "delta": 0.628163099986049,
                    "gamma": 0.031524471889867844,
                    "vega": 0.029989313090068137,
                    "price": 6.400000095367432
                },
                {
                    "contract_localSymbol": "NOW   260424C00105000",
                    "contract_strike": 105.0,
                    "contract_right": "C",
                    "Bid": 3.9,
                    "Ask": 4.1,
                    "IV": 1.5165990215400225,
                    "call_open_interest": 5575.0,
                    "put_open_interest": 0.0,
                    "theta": -1.1088583241996168,
                    "delta": 0.4641279761088919,
                    "gamma": 0.032927900318342786,
                    "vega": 0.0320100044791074,
                    "price": 4.0
                },
                {
                    "contract_localSymbol": "NOW   260424C00110000",
                    "contract_strike": 110.0,
                    "contract_right": "C",
                    "Bid": 2.2,
                    "Ask": 2.35,
                    "IV": 1.5164311902351375,
                    "call_open_interest": 3694.0,
                    "put_open_interest": 0.0,
                    "theta": -0.987459030728906,
                    "delta": 0.3132921079000957,
                    "gamma": 0.0293581679407843,
                    "vega": 0.029079760549270084,
                    "price": 2.299999952316284
                },
                {
                    "contract_localSymbol": "NOW   260424C00115000",
                    "contract_strike": 115.0,
                    "contract_right": "C",
                    "Bid": 1.25,
                    "Ask": 1.3,
                    "IV": 1.5212954269739798,
                    "call_open_interest": 2502.0,
                    "put_open_interest": 0.0,
                    "theta": -0.7676643466153035,
                    "delta": 0.1943939129466003,
                    "gamma": 0.022692008785506628,
                    "vega": 0.022477239137496774,
                    "price": 1.2699999809265137
                },
                {
                    "contract_localSymbol": "NOW   260424C00120000",
                    "contract_strike": 120.0,
                    "contract_right": "C",
                    "Bid": 0.65,
                    "Ask": 0.75,
                    "IV": 1.572920648032752,
                    "call_open_interest": 4757.0,
                    "put_open_interest": 0.0,
                    "theta": -0.572761552715745,
                    "delta": 0.11862417438916077,
                    "gamma": 0.015844869114686137,
                    "vega": 0.014766841032613831,
                    "price": 0.699999988079071
                },
                {
                    "contract_localSymbol": "NOW   260424C00085000",
                    "contract_strike": 85.0,
                    "contract_right": "C",
                    "Bid": 17.8,
                    "Ask": 18.6,
                    "IV": 1.5373717527790565,
                    "call_open_interest": 1788.0,
                    "put_open_interest": 0.0,
                    "theta": -0.12017130433534362,
                    "delta": 0.9549787304202689,
                    "gamma": 0.007750010422481013,
                    "vega": 0.006752375729472959,
                    "price": 18.299999237060547
                },
                {
                    "contract_localSymbol": "NOW   260424C00090000",
                    "contract_strike": 90.0,
                    "contract_right": "C",
                    "Bid": 13.2,
                    "Ask": 14.0,
                    "IV": 1.5072224984181724,
                    "call_open_interest": 2037.0,
                    "put_open_interest": 0.0,
                    "theta": -0.5233967166538396,
                    "delta": 0.8912388027147129,
                    "gamma": 0.015551620885998926,
                    "vega": 0.01620259952010983,
                    "price": 13.84031963
                },
                {
                    "contract_localSymbol": "NOW   260424C00095000",
                    "contract_strike": 95.0,
                    "contract_right": "C",
                    "Bid": 9.0,
                    "Ask": 10.0,
                    "IV": 1.4964141195573375,
                    "call_open_interest": 1346.0,
                    "put_open_interest": 0.0,
                    "theta": -0.8187959191938909,
                    "delta": 0.779701978962128,
                    "gamma": 0.02484984116691479,
                    "vega": 0.02390615773845539,
                    "price": 9.300000190734863
                },
                {
                    "contract_localSymbol": "NOW   260424P00100000",
                    "contract_strike": 100.0,
                    "contract_right": "P",
                    "Bid": 3.1,
                    "Ask": 3.4,
                    "IV": 1.492651659270157,
                    "call_open_interest": 0.0,
                    "put_open_interest": 1704.0,
                    "theta": -1.0288630144888238,
                    "delta": -0.37118153356931183,
                    "gamma": 0.031810744645153766,
                    "vega": 0.029991098559914775,
                    "price": 3.26383305
                },
                {
                    "contract_localSymbol": "NOW   260424P00105000",
                    "contract_strike": 105.0,
                    "contract_right": "P",
                    "Bid": 5.6,
                    "Ask": 6.3,
                    "IV": 1.4944858614374992,
                    "call_open_interest": 0.0,
                    "put_open_interest": 535.0,
                    "theta": -1.081922696122357,
                    "delta": -0.5372611786944,
                    "gamma": 0.03342648096388801,
                    "vega": 0.032010115652141735,
                    "price": 6.199999809265137
                },
                {
                    "contract_localSymbol": "NOW   260424P00110000",
                    "contract_strike": 110.0,
                    "contract_right": "P",
                    "Bid": 8.8,
                    "Ask": 10.0,
                    "IV": null,
                    "call_open_interest": 0.0,
                    "put_open_interest": 397.0,
                    "theta": null,
                    "delta": null,
                    "gamma": null,
                    "vega": null,
                    "price": 10.0
                },
                {
                    "contract_localSymbol": "NOW   260424P00115000",
                    "contract_strike": 115.0,
                    "contract_right": "P",
                    "Bid": 12.5,
                    "Ask": 14.5,
                    "IV": null,
                    "call_open_interest": 0.0,
                    "put_open_interest": 284.0,
                    "theta": null,
                    "delta": null,
                    "gamma": null,
                    "vega": null,
                    "price": 13.0792675
                },
                {
                    "contract_localSymbol": "NOW   260424P00120000",
                    "contract_strike": 120.0,
                    "contract_right": "P",
                    "Bid": 17.1,
                    "Ask": 19.1,
                    "IV": null,
                    "call_open_interest": 0.0,
                    "put_open_interest": 111.0,
                    "theta": null,
                    "delta": null,
                    "gamma": null,
                    "vega": null,
                    "price": 19.100000381469727
                },
                {
                    "contract_localSymbol": "NOW   260424P00085000",
                    "contract_strike": 85.0,
                    "contract_right": "P",
                    "Bid": 0.25,
                    "Ask": 0.3,
                    "IV": 1.5600209955813242,
                    "call_open_interest": 0.0,
                    "put_open_interest": 10603.0,
                    "theta": -0.25999999046325684,
                    "delta": -0.04695452710240071,
                    "gamma": 0.007914495839299901,
                    "vega": 0.00848127021185352,
                    "price": 0.25999999046325684
                },
                {
                    "contract_localSymbol": "NOW   260424P00090000",
                    "contract_strike": 90.0,
                    "contract_right": "P",
                    "Bid": 0.65,
                    "Ask": 0.7,
                    "IV": 1.507986442925705,
                    "call_open_interest": 0.0,
                    "put_open_interest": 5342.0,
                    "theta": -0.5145499949639791,
                    "delta": -0.10889918814614169,
                    "gamma": 0.015558519621124846,
                    "vega": 0.01620292243306476,
                    "price": 0.6600000262260437
                },
                {
                    "contract_localSymbol": "NOW   260424P00095000",
                    "contract_strike": 95.0,
                    "contract_right": "P",
                    "Bid": 1.55,
                    "Ask": 1.6,
                    "IV": 1.4801517297306137,
                    "call_open_interest": 0.0,
                    "put_open_interest": 4335.0,
                    "theta": -0.7956295868905132,
                    "delta": -0.21818974232758864,
                    "gamma": 0.024989912214263128,
                    "vega": 0.023906927072852246,
                    "price": 1.600000023841858
                },
                {
                    "contract_localSymbol": "NOW   260424C00104000",
                    "contract_strike": 104.0,
                    "contract_right": "C",
                    "Bid": 4.3,
                    "Ask": 4.6,
                    "IV": 1.5143850127352119,
                    "call_open_interest": 760.0,
                    "put_open_interest": 0.0,
                    "theta": -1.1111889609297285,
                    "delta": 0.4966672506572285,
                    "gamma": 0.03308463063534081,
                    "vega": 0.03185217523067596,
                    "price": 4.400000095367432
                },
                {
                    "contract_localSymbol": "NOW   260424C00101000",
                    "contract_strike": 101.0,
                    "contract_right": "C",
                    "Bid": 5.6,
                    "Ask": 6.1,
                    "IV": 1.5305625498139064,
                    "call_open_interest": 902.0,
                    "put_open_interest": 0.0,
                    "theta": -1.0949800741729505,
                    "delta": 0.5949410551117137,
                    "gamma": 0.03188743461065777,
                    "vega": 0.03137326580927269,
                    "price": 5.800000190734863
                },
                {
                    "contract_localSymbol": "NOW   260424C00102000",
                    "contract_strike": 102.0,
                    "contract_right": "C",
                    "Bid": 5.2,
                    "Ask": 5.5,
                    "IV": 1.529982142090802,
                    "call_open_interest": 1780.0,
                    "put_open_interest": 0.0,
                    "theta": -1.1090694182874266,
                    "delta": 0.5622623113362057,
                    "gamma": 0.032333389318324725,
                    "vega": 0.03153302566314764,
                    "price": 5.400000095367432
                },
                {
                    "contract_localSymbol": "NOW   260424C00103000",
                    "contract_strike": 103.0,
                    "contract_right": "C",
                    "Bid": 4.7,
                    "Ask": 5.0,
                    "IV": 1.51141764818066,
                    "call_open_interest": 454.0,
                    "put_open_interest": 0.0,
                    "theta": -1.1100402786413652,
                    "delta": 0.5293537725834224,
                    "gamma": 0.033170802738626014,
                    "vega": 0.03169407622138731,
                    "price": 4.849999904632568
                },
                {
                    "contract_localSymbol": "NOW   260424C00106000",
                    "contract_strike": 106.0,
                    "contract_right": "C",
                    "Bid": 3.4,
                    "Ask": 3.7,
                    "IV": 1.53813196125905,
                    "call_open_interest": 388.0,
                    "put_open_interest": 0.0,
                    "theta": -1.1147765607572167,
                    "delta": 0.4337158339326048,
                    "gamma": 0.03219256446688208,
                    "vega": 0.030903963093138476,
                    "price": 3.5999999046325684
                },
                {
                    "contract_localSymbol": "NOW   260424C00107000",
                    "contract_strike": 107.0,
                    "contract_right": "C",
                    "Bid": 3.0,
                    "Ask": 3.3,
                    "IV": 1.5068060580339486,
                    "call_open_interest": 632.0,
                    "put_open_interest": 0.0,
                    "theta": -1.0695867304566462,
                    "delta": 0.40024103362772906,
                    "gamma": 0.03218959765913934,
                    "vega": 0.03105689947604162,
                    "price": 3.2100000381469727
                },
                {
                    "contract_localSymbol": "NOW   260424C00108000",
                    "contract_strike": 108.0,
                    "contract_right": "C",
                    "Bid": 2.75,
                    "Ask": 2.95,
                    "IV": 1.5061881837209856,
                    "call_open_interest": 376.0,
                    "put_open_interest": 0.0,
                    "theta": -1.0479812445461048,
                    "delta": 0.3689830116906901,
                    "gamma": 0.031572005391569215,
                    "vega": 0.03120713824859811,
                    "price": 2.86313796
                },
                {
                    "contract_localSymbol": "NOW   260424C00109000",
                    "contract_strike": 109.0,
                    "contract_right": "C",
                    "Bid": 2.45,
                    "Ask": 2.65,
                    "IV": 1.5258386160434023,
                    "call_open_interest": 338.0,
                    "put_open_interest": 0.0,
                    "theta": -1.0303003722536204,
                    "delta": 0.34274583578199147,
                    "gamma": 0.030250840073634804,
                    "vega": 0.028941837420854544,
                    "price": 2.3499999046325684
                },
                {
                    "contract_localSymbol": "NOW   260424C00111000",
                    "contract_strike": 111.0,
                    "contract_right": "C",
                    "Bid": 1.9,
                    "Ask": 2.1,
                    "IV": 1.5404732824837304,
                    "call_open_interest": 261.0,
                    "put_open_interest": 0.0,
                    "theta": -0.9706441873072092,
                    "delta": 0.28955389446396695,
                    "gamma": 0.027969760983989515,
                    "vega": 0.025906442834664922,
                    "price": 2.0
                },
                {
                    "contract_localSymbol": "NOW   260424C00112000",
                    "contract_strike": 112.0,
                    "contract_right": "C",
                    "Bid": 1.7,
                    "Ask": 1.9,
                    "IV": 1.5218426633508348,
                    "call_open_interest": 538.0,
                    "put_open_interest": 0.0,
                    "theta": -0.9095944054312765,
                    "delta": 0.26218633606683195,
                    "gamma": 0.026858838560176918,
                    "vega": 0.026028305998609946,
                    "price": 1.75
                },
                {
                    "contract_localSymbol": "NOW   260424C00113000",
                    "contract_strike": 113.0,
                    "contract_right": "C",
                    "Bid": 1.5,
                    "Ask": 1.65,
                    "IV": 1.4890853525695225,
                    "call_open_interest": 380.0,
                    "put_open_interest": 0.0,
                    "theta": -0.8357938129154735,
                    "delta": 0.23151235696717276,
                    "gamma": 0.025780143363519057,
                    "vega": 0.026152180682610382,
                    "price": 1.5
                },
                {
                    "contract_localSymbol": "NOW   260424C00114000",
                    "contract_strike": 114.0,
                    "contract_right": "C",
                    "Bid": 1.35,
                    "Ask": 1.5,
                    "IV": 1.5299955583720881,
                    "call_open_interest": 2164.0,
                    "put_open_interest": 0.0,
                    "theta": -0.8249787939954317,
                    "delta": 0.2166489105213902,
                    "gamma": 0.024107444477871852,
                    "vega": 0.022375282987681766,
                    "price": 1.350000023841858
                },
                {
                    "contract_localSymbol": "NOW   260424C00116000",
                    "contract_strike": 116.0,
                    "contract_right": "C",
                    "Bid": 1.05,
                    "Ask": 1.15,
                    "IV": 1.5715937432334592,
                    "call_open_interest": 353.0,
                    "put_open_interest": 0.0,
                    "theta": -0.7655268971921542,
                    "delta": 0.18312801072532303,
                    "gamma": 0.021206555793133075,
                    "vega": 0.02257272195706328,
                    "price": 1.11564243
                },
                {
                    "contract_localSymbol": "NOW   260424C00117000",
                    "contract_strike": 117.0,
                    "contract_right": "C",
                    "Bid": 0.9,
                    "Ask": 1.05,
                    "IV": 1.5231689338241916,
                    "call_open_interest": 236.0,
                    "put_open_interest": 0.0,
                    "theta": -0.6709129032790706,
                    "delta": 0.15685962372460913,
                    "gamma": 0.01978710778434617,
                    "vega": 0.018554894506107145,
                    "price": 0.9300000071525574
                },
                {
                    "contract_localSymbol": "NOW   260424C00118000",
                    "contract_strike": 118.0,
                    "contract_right": "C",
                    "Bid": 0.75,
                    "Ask": 0.95,
                    "IV": 1.5431871259210075,
                    "call_open_interest": 209.0,
                    "put_open_interest": 0.0,
                    "theta": -0.6405639378278652,
                    "delta": 0.1436724048307826,
                    "gamma": 0.018406834539404365,
                    "vega": 0.018634697743479478,
                    "price": 0.8500000238418579
                },
                {
                    "contract_localSymbol": "NOW   260424C00091000",
                    "contract_strike": 91.0,
                    "contract_right": "C",
                    "Bid": 11.6,
                    "Ask": 13.3,
                    "IV": 1.9628910839100941,
                    "call_open_interest": 273.0,
                    "put_open_interest": 0.0,
                    "theta": -0.8187727069960289,
                    "delta": 0.8172467277300433,
                    "gamma": 0.016983392333098674,
                    "vega": 0.0199103647225769,
                    "price": 12.97245884
                },
                {
                    "contract_localSymbol": "NOW   260424C00092000",
                    "contract_strike": 92.0,
                    "contract_right": "C",
                    "Bid": 10.7,
                    "Ask": 13.0,
                    "IV": 1.5144958353437579,
                    "call_open_interest": 216.0,
                    "put_open_interest": 0.0,
                    "theta": -0.6532693988247282,
                    "delta": 0.8508266892835431,
                    "gamma": 0.019294250331456552,
                    "vega": 0.020029572687992214,
                    "price": 13.0
                },
                {
                    "contract_localSymbol": "NOW   260424C00093000",
                    "contract_strike": 93.0,
                    "contract_right": "C",
                    "Bid": 10.4,
                    "Ask": 11.6,
                    "IV": 1.5123676399765913,
                    "call_open_interest": 344.0,
                    "put_open_interest": 0.0,
                    "theta": -0.7134013763766315,
                    "delta": 0.8279659318244232,
                    "gamma": 0.021156814794949755,
                    "vega": 0.020141628325363925,
                    "price": 12.270000457763672
                },
                {
                    "contract_localSymbol": "NOW   260424C00094000",
                    "contract_strike": 94.0,
                    "contract_right": "C",
                    "Bid": 9.7,
                    "Ask": 10.8,
                    "IV": 1.6726978353384363,
                    "call_open_interest": 335.0,
                    "put_open_interest": 0.0,
                    "theta": -0.9049071035851749,
                    "delta": 0.7836699999357312,
                    "gamma": 0.022000593458153056,
                    "vega": 0.023773198448314048,
                    "price": 10.50912952
                },
                {
                    "contract_localSymbol": "NOW   260424C00096000",
                    "contract_strike": 96.0,
                    "contract_right": "C",
                    "Bid": 8.3,
                    "Ask": 9.3,
                    "IV": 1.5082064577784686,
                    "call_open_interest": 523.0,
                    "put_open_interest": 0.0,
                    "theta": -0.8852065344857409,
                    "delta": 0.7511857324469524,
                    "gamma": 0.02647245250342955,
                    "vega": 0.024036114546927223,
                    "price": 9.5600004196167
                },
                {
                    "contract_localSymbol": "NOW   260424C00097000",
                    "contract_strike": 97.0,
                    "contract_right": "C",
                    "Bid": 7.8,
                    "Ask": 8.6,
                    "IV": 1.4617732054252333,
                    "call_open_interest": 544.0,
                    "put_open_interest": 0.0,
                    "theta": -0.8975062555566835,
                    "delta": 0.726785770559617,
                    "gamma": 0.02858176305144371,
                    "vega": 0.02725090716565859,
                    "price": 7.800000190734863
                },
                {
                    "contract_localSymbol": "NOW   260424C00098000",
                    "contract_strike": 98.0,
                    "contract_right": "C",
                    "Bid": 7.1,
                    "Ask": 7.8,
                    "IV": 1.4787831299761731,
                    "call_open_interest": 589.0,
                    "put_open_interest": 0.0,
                    "theta": -0.9572008894950135,
                    "delta": 0.6941974050835426,
                    "gamma": 0.029809495500928672,
                    "vega": 0.02739568939646375,
                    "price": 8.25
                },
                {
                    "contract_localSymbol": "NOW   260424C00099000",
                    "contract_strike": 99.0,
                    "contract_right": "C",
                    "Bid": 6.6,
                    "Ask": 7.3,
                    "IV": 1.4773098054955296,
                    "call_open_interest": 524.0,
                    "put_open_interest": 0.0,
                    "theta": -0.9958865414325656,
                    "delta": 0.6626403626618086,
                    "gamma": 0.031093581670431376,
                    "vega": 0.029835141109890273,
                    "price": 6.300000190734863
                },
                {
                    "contract_localSymbol": "NOW   260424P00101000",
                    "contract_strike": 101.0,
                    "contract_right": "P",
                    "Bid": 3.6,
                    "Ask": 4.1,
                    "IV": 1.6867294335447007,
                    "call_open_interest": 0.0,
                    "put_open_interest": 566.0,
                    "theta": -1.1972790963776059,
                    "delta": -0.40935270839583365,
                    "gamma": 0.028983954038801996,
                    "vega": 0.0313636213319608,
                    "price": 3.799999952316284
                },
                {
                    "contract_localSymbol": "NOW   260424P00102000",
                    "contract_strike": 102.0,
                    "contract_right": "P",
                    "Bid": 4.1,
                    "Ask": 4.6,
                    "IV": 1.4770394226960413,
                    "call_open_interest": 0.0,
                    "put_open_interest": 140.0,
                    "theta": -1.060206843670955,
                    "delta": -0.43728956998292684,
                    "gamma": 0.03349800293319066,
                    "vega": 0.031536823304331385,
                    "price": 4.489999771118164
                },
                {
                    "contract_localSymbol": "NOW   260424P00103000",
                    "contract_strike": 103.0,
                    "contract_right": "P",
                    "Bid": 4.6,
                    "Ask": 4.9,
                    "IV": 1.5030726447367553,
                    "call_open_interest": 0.0,
                    "put_open_interest": 255.0,
                    "theta": -1.0934562289277532,
                    "delta": -0.47087595760849926,
                    "gamma": 0.03337010094061855,
                    "vega": 0.03169479934088404,
                    "price": 4.699999809265137
                },
                {
                    "contract_localSymbol": "NOW   260424P00104000",
                    "contract_strike": 104.0,
                    "contract_right": "P",
                    "Bid": 5.1,
                    "Ask": 5.8,
                    "IV": 1.6396579404244476,
                    "call_open_interest": 0.0,
                    "put_open_interest": 66.0,
                    "theta": -1.1923652041857062,
                    "delta": -0.49948766538592776,
                    "gamma": 0.030575829527312928,
                    "vega": 0.03184172928913043,
                    "price": 5.489999771118164
                },
                {
                    "contract_localSymbol": "NOW   260424P00106000",
                    "contract_strike": 106.0,
                    "contract_right": "P",
                    "Bid": 6.2,
                    "Ask": 7.3,
                    "IV": 1.5429349814553253,
                    "call_open_interest": 0.0,
                    "put_open_interest": 114.0,
                    "theta": -1.1077301875994852,
                    "delta": -0.5661186808760509,
                    "gamma": 0.032115046151803606,
                    "vega": 0.0309025236301661,
                    "price": 6.0
                },
                {
                    "contract_localSymbol": "NOW   260424P00107000",
                    "contract_strike": 107.0,
                    "contract_right": "P",
                    "Bid": 6.9,
                    "Ask": 7.9,
                    "IV": null,
                    "call_open_interest": 0.0,
                    "put_open_interest": 27.0,
                    "theta": null,
                    "delta": null,
                    "gamma": null,
                    "vega": null,
                    "price": 7.210000038146973
                },
                {
                    "contract_localSymbol": "NOW   260424P00108000",
                    "contract_strike": 108.0,
                    "contract_right": "P",
                    "Bid": 7.5,
                    "Ask": 8.6,
                    "IV": null,
                    "call_open_interest": 0.0,
                    "put_open_interest": 64.0,
                    "theta": null,
                    "delta": null,
                    "gamma": null,
                    "vega": null,
                    "price": 8.600000381469727
                },
                {
                    "contract_localSymbol": "NOW   260424P00109000",
                    "contract_strike": 109.0,
                    "contract_right": "P",
                    "Bid": 8.1,
                    "Ask": 8.7,
                    "IV": null,
                    "call_open_interest": 0.0,
                    "put_open_interest": 69.0,
                    "theta": null,
                    "delta": null,
                    "gamma": null,
                    "vega": null,
                    "price": 8.699999809265137
                },
                {
                    "contract_localSymbol": "NOW   260424P00111000",
                    "contract_strike": 111.0,
                    "contract_right": "P",
                    "Bid": 9.5,
                    "Ask": 10.8,
                    "IV": null,
                    "call_open_interest": 0.0,
                    "put_open_interest": 55.0,
                    "theta": null,
                    "delta": null,
                    "gamma": null,
                    "vega": null,
                    "price": 10.800000190734863
                },
                {
                    "contract_localSymbol": "NOW   260424P00112000",
                    "contract_strike": 112.0,
                    "contract_right": "P",
                    "Bid": 10.3,
                    "Ask": 11.6,
                    "IV": null,
                    "call_open_interest": 0.0,
                    "put_open_interest": 5.0,
                    "theta": null,
                    "delta": null,
                    "gamma": null,
                    "vega": null,
                    "price": 11.600000381469727
                },
                {
                    "contract_localSymbol": "NOW   260424P00113000",
                    "contract_strike": 113.0,
                    "contract_right": "P",
                    "Bid": 11.1,
                    "Ask": 12.4,
                    "IV": null,
                    "call_open_interest": 0.0,
                    "put_open_interest": 67.0,
                    "theta": null,
                    "delta": null,
                    "gamma": null,
                    "vega": null,
                    "price": 12.399999618530273
                },
                {
                    "contract_localSymbol": "NOW   260424P00114000",
                    "contract_strike": 114.0,
                    "contract_right": "P",
                    "Bid": 11.9,
                    "Ask": 13.2,
                    "IV": null,
                    "call_open_interest": 0.0,
                    "put_open_interest": 6.0,
                    "theta": null,
                    "delta": null,
                    "gamma": null,
                    "vega": null,
                    "price": 12.23627281
                },
                {
                    "contract_localSymbol": "NOW   260424P00116000",
                    "contract_strike": 116.0,
                    "contract_right": "P",
                    "Bid": 11.6,
                    "Ask": 15.7,
                    "IV": null,
                    "call_open_interest": 0.0,
                    "put_open_interest": 1.0,
                    "theta": null,
                    "delta": null,
                    "gamma": null,
                    "vega": null,
                    "price": 15.699999809265137
                },
                {
                    "contract_localSymbol": "NOW   260424P00117000",
                    "contract_strike": 117.0,
                    "contract_right": "P",
                    "Bid": 12.4,
                    "Ask": 16.5,
                    "IV": null,
                    "call_open_interest": 0.0,
                    "put_open_interest": 0.0,
                    "theta": null,
                    "delta": null,
                    "gamma": null,
                    "vega": null,
                    "price": 14.80206203
                },
                {
                    "contract_localSymbol": "NOW   260424P00118000",
                    "contract_strike": 118.0,
                    "contract_right": "P",
                    "Bid": 13.3,
                    "Ask": 19.0,
                    "IV": null,
                    "call_open_interest": 0.0,
                    "put_open_interest": 68.0,
                    "theta": null,
                    "delta": null,
                    "gamma": null,
                    "vega": null,
                    "price": 15.69131088
                },
                {
                    "contract_localSymbol": "NOW   260424P00091000",
                    "contract_strike": 91.0,
                    "contract_right": "P",
                    "Bid": 0.75,
                    "Ask": 0.8,
                    "IV": 1.5004431892185806,
                    "call_open_interest": 0.0,
                    "put_open_interest": 255.0,
                    "theta": -0.5701385968732767,
                    "delta": -0.12709359389992697,
                    "gamma": 0.0174155090121297,
                    "vega": 0.016295930891651933,
                    "price": 0.800000011920929
                },
                {
                    "contract_localSymbol": "NOW   260424P00092000",
                    "contract_strike": 92.0,
                    "contract_right": "P",
                    "Bid": 0.9,
                    "Ask": 1.0,
                    "IV": 1.4738703678036438,
                    "call_open_interest": 0.0,
                    "put_open_interest": 945.0,
                    "theta": -0.609851897115084,
                    "delta": -0.14298286030140822,
                    "gamma": 0.01930903293803336,
                    "vega": 0.01818639338600092,
                    "price": 0.949999988079071
                },
                {
                    "contract_localSymbol": "NOW   260424P00093000",
                    "contract_strike": 93.0,
                    "contract_right": "P",
                    "Bid": 1.05,
                    "Ask": 1.15,
                    "IV": 1.4693561585791468,
                    "call_open_interest": 0.0,
                    "put_open_interest": 411.0,
                    "theta": -0.6677146793565555,
                    "delta": -0.1659363521245008,
                    "gamma": 0.021274812139209506,
                    "vega": 0.020142004393429502,
                    "price": 1.100000023841858
                },
                {
                    "contract_localSymbol": "NOW   260424P00094000",
                    "contract_strike": 94.0,
                    "contract_right": "P",
                    "Bid": 1.25,
                    "Ask": 1.4,
                    "IV": 1.442850500941379,
                    "call_open_interest": 0.0,
                    "put_open_interest": 536.0,
                    "theta": -0.7070521549515217,
                    "delta": -0.18621101302565207,
                    "gamma": 0.023367644240753677,
                    "vega": 0.020255395821200173,
                    "price": 1.3300000429153442
                },
                {
                    "contract_localSymbol": "NOW   260424P00096000",
                    "contract_strike": 96.0,
                    "contract_right": "P",
                    "Bid": 1.75,
                    "Ask": 1.95,
                    "IV": 1.4948929346861506,
                    "call_open_interest": 0.0,
                    "put_open_interest": 510.0,
                    "theta": -0.8643074185057693,
                    "delta": -0.24736700820110558,
                    "gamma": 0.026618231419898997,
                    "vega": 0.02403992080768491,
                    "price": 1.850000023841858
                },
                {
                    "contract_localSymbol": "NOW   260424P00097000",
                    "contract_strike": 97.0,
                    "contract_right": "P",
                    "Bid": 2.1,
                    "Ask": 2.25,
                    "IV": 1.488853004202908,
                    "call_open_interest": 0.0,
                    "put_open_interest": 499.0,
                    "theta": -0.9085097208248462,
                    "delta": -0.2763136441415301,
                    "gamma": 0.028213237682101017,
                    "vega": 0.027251057226442832,
                    "price": 2.200000047683716
                },
                {
                    "contract_localSymbol": "NOW   260424P00098000",
                    "contract_strike": 98.0,
                    "contract_right": "P",
                    "Bid": 2.45,
                    "Ask": 2.6,
                    "IV": 1.4896216911759759,
                    "call_open_interest": 0.0,
                    "put_open_interest": 1055.0,
                    "theta": -0.9555324383372903,
                    "delta": -0.3068552510855078,
                    "gamma": 0.029649125782903872,
                    "vega": 0.027397163619117038,
                    "price": 2.549999952316284
                },
                {
                    "contract_localSymbol": "NOW   260424P00099000",
                    "contract_strike": 99.0,
                    "contract_right": "P",
                    "Bid": 2.85,
                    "Ask": 3.0,
                    "IV": 1.4589263496743066,
                    "call_open_interest": 0.0,
                    "put_open_interest": 447.0,
                    "theta": -0.9720273492005652,
                    "delta": -0.3360112796154484,
                    "gamma": 0.031452801118332985,
                    "vega": 0.029836554782204594,
                    "price": 2.9000000953674316
                },
                {
                    "contract_localSymbol": "NOW   260424C00087000",
                    "contract_strike": 87.0,
                    "contract_right": "C",
                    "Bid": 15.1,
                    "Ask": 18.0,
                    "IV": 1.9801388908599766,
                    "call_open_interest": 60.0,
                    "put_open_interest": 0.0,
                    "theta": -0.04970515608486892,
                    "delta": 0.8829861600263458,
                    "gamma": 0.01244603571788065,
                    "vega": 0.01592043416416189,
                    "price": 16.229999542236328
                },
                {
                    "contract_localSymbol": "NOW   260424P00089000",
                    "contract_strike": 89.0,
                    "contract_right": "P",
                    "Bid": 0.5,
                    "Ask": 0.6,
                    "IV": 1.453136360029679,
                    "call_open_interest": 0.0,
                    "put_open_interest": 886.0,
                    "theta": -0.41262962793798214,
                    "delta": -0.08508314536081854,
                    "gamma": 0.013435484024327246,
                    "vega": 0.012656572744984995,
                    "price": 0.5600000023841858
                },
                {
                    "contract_localSymbol": "NOW   260424C00088000",
                    "contract_strike": 88.0,
                    "contract_right": "C",
                    "Bid": 14.1,
                    "Ask": 15.9,
                    "IV": 1.3497201950099178,
                    "call_open_interest": 457.0,
                    "put_open_interest": 0.0,
                    "theta": -0.29210493361096207,
                    "delta": 0.9426807221172198,
                    "gamma": 0.010669833603663416,
                    "vega": 0.00948970819615269,
                    "price": 15.75
                },
                {
                    "contract_localSymbol": "NOW   260424C00089000",
                    "contract_strike": 89.0,
                    "contract_right": "C",
                    "Bid": 13.4,
                    "Ask": 15.0,
                    "IV": null,
                    "call_open_interest": 89.0,
                    "put_open_interest": 0.0,
                    "theta": null,
                    "delta": null,
                    "gamma": null,
                    "vega": null,
                    "price": 13.899999618530273
                },
                {
                    "contract_localSymbol": "NOW   260424C00097500",
                    "contract_strike": 97.5,
                    "contract_right": "C",
                    "Bid": 7.4,
                    "Ask": 8.2,
                    "IV": 1.8302519091630456,
                    "call_open_interest": 179.0,
                    "put_open_interest": 0.0,
                    "theta": -1.2075975525866598,
                    "delta": 0.6816284895771282,
                    "gamma": 0.024591745047574803,
                    "vega": 0.029584877211345173,
                    "price": 7.949999809265137
                },
                {
                    "contract_localSymbol": "NOW   260424C00098500",
                    "contract_strike": 98.5,
                    "contract_right": "C",
                    "Bid": 6.5,
                    "Ask": 7.5,
                    "IV": 1.5386691811130548,
                    "call_open_interest": 215.0,
                    "put_open_interest": 0.0,
                    "theta": -1.0253523816868453,
                    "delta": 0.6739346447031757,
                    "gamma": 0.029514491158382554,
                    "vega": 0.029754990337188758,
                    "price": 7.300000190734863
                },
                {
                    "contract_localSymbol": "NOW   260424P00087000",
                    "contract_strike": 87.0,
                    "contract_right": "P",
                    "Bid": 0.35,
                    "Ask": 0.4,
                    "IV": 1.5015768364783235,
                    "call_open_interest": 0.0,
                    "put_open_interest": 846.0,
                    "theta": -0.3400964775951844,
                    "delta": -0.0632361371171933,
                    "gamma": 0.010368300783824965,
                    "vega": 0.009437084512364358,
                    "price": 0.4000000059604645
                },
                {
                    "contract_localSymbol": "NOW   260424P00088000",
                    "contract_strike": 88.0,
                    "contract_right": "P",
                    "Bid": 0.4,
                    "Ask": 0.5,
                    "IV": 1.483453896842601,
                    "call_open_interest": 0.0,
                    "put_open_interest": 1320.0,
                    "theta": -0.37883162892380706,
                    "delta": -0.0736339227164721,
                    "gamma": 0.01183429801876887,
                    "vega": 0.01258332161651976,
                    "price": 0.44999998807907104
                },
                {
                    "contract_localSymbol": "NOW   260424P00097500",
                    "contract_strike": 97.5,
                    "contract_right": "P",
                    "Bid": 2.2,
                    "Ask": 2.45,
                    "IV": 1.4978900897396938,
                    "call_open_interest": 0.0,
                    "put_open_interest": 211.0,
                    "theta": -0.93876840209608,
                    "delta": -0.29244416885110636,
                    "gamma": 0.028804877627950167,
                    "vega": 0.027323751628996362,
                    "price": 2.4000000953674316
                },
                {
                    "contract_localSymbol": "NOW   260424P00098500",
                    "contract_strike": 98.5,
                    "contract_right": "P",
                    "Bid": 2.6,
                    "Ask": 2.9,
                    "IV": 1.4624796156215392,
                    "call_open_interest": 0.0,
                    "put_open_interest": 2394.0,
                    "theta": -0.9574656246216036,
                    "delta": -0.31987813473904436,
                    "gamma": 0.03082683432575956,
                    "vega": 0.027475347035207154,
                    "price": 2.75
                },
                {
                    "contract_localSymbol": "NOW   260424C00086000",
                    "contract_strike": 86.0,
                    "contract_right": "C",
                    "Bid": 15.9,
                    "Ask": 19.0,
                    "IV": null,
                    "call_open_interest": 50.0,
                    "put_open_interest": 0.0,
                    "theta": null,
                    "delta": null,
                    "gamma": null,
                    "vega": null,
                    "price": 19.0
                }
            ],
            "recommendation": {
                "expected_move": 9.2,
                "average_percent_move": 8.760942826693919,
                "lower_boundary": 84.78499756,
                "upper_boundary": 121.58499756
            }
        }
    ],
    "historic_move": [
        {
            "date": "20250409",
            "open": 145.0,
            "high": 166.33,
            "low": 144.64,
            "close": 165.19,
            "candle_length": 21.690000000000026,
            "percent_move": 13.130334766027016
        },
        {
            "date": "20250407",
            "open": 137.6,
            "high": 151.73,
            "low": 135.73,
            "close": 147.1,
            "candle_length": 16.0,
            "percent_move": 10.876954452753228
        },
        {
            "date": "20260205",
            "open": 109.26,
            "high": 112.09,
            "low": 101.72,
            "close": 102.63,
            "candle_length": 10.370000000000005,
            "percent_move": 10.104258014225865
        },
        {
            "date": "20260409",
            "open": 96.5,
            "high": 97.16,
            "low": 88.66,
            "close": 89.81,
            "candle_length": 8.5,
            "percent_move": 9.464424897004788
        },
        {
            "date": "20260410",
            "open": 88.91,
            "high": 88.91,
            "low": 81.24,
            "close": 83.0,
            "candle_length": 7.670000000000002,
            "percent_move": 9.240963855421688
        },
        {
            "date": "20260408",
            "open": 104.76,
            "high": 105.58,
            "low": 96.96,
            "close": 97.47,
            "candle_length": 8.620000000000005,
            "percent_move": 8.843746793885304
        },
        {
            "date": "20250408",
            "open": 153.6,
            "high": 155.18,
            "low": 142.64,
            "close": 145.52,
            "candle_length": 12.54000000000002,
            "percent_move": 8.617372182517881
        },
        {
            "date": "20240530",
            "open": 138.2,
            "high": 138.51,
            "low": 128.03,
            "close": 128.66,
            "candle_length": 10.47999999999999,
            "percent_move": 8.145499766827289
        },
        {
            "date": "20240725",
            "open": 157.87,
            "high": 170.07,
            "low": 156.61,
            "close": 165.76,
            "candle_length": 13.45999999999998,
            "percent_move": 8.120173745173734
        },
        {
            "date": "20230727",
            "open": 119.6,
            "high": 120.13,
            "low": 111.34,
            "close": 111.98,
            "candle_length": 8.789999999999992,
            "percent_move": 7.849616002857646
        },
        {
            "date": "20251030",
            "open": 185.35,
            "high": 192.97,
            "low": 179.38,
            "close": 186.94,
            "candle_length": 13.590000000000003,
            "percent_move": 7.269712207125282
        },
        {
            "date": "20260203",
            "open": 115.02,
            "high": 115.89,
            "low": 108.1,
            "close": 109.77,
            "candle_length": 7.790000000000006,
            "percent_move": 7.096656645713771
        },
        {
            "date": "20250807",
            "open": 184.4,
            "high": 184.58,
            "low": 172.4,
            "close": 174.82,
            "candle_length": 12.180000000000007,
            "percent_move": 6.967166228120357
        },
        {
            "date": "20250724",
            "open": 206.93,
            "high": 210.2,
            "low": 196.4,
            "close": 199.24,
            "candle_length": 13.799999999999983,
            "percent_move": 6.926320016061023
        }
    ]
}